pcompress/__init__.py
pcompress/record.py
pcompress-1.1.2.dist-info/WHEEL
pcompress-1.1.2.dist-info/METADATA
pcompress-1.1.2.dist-info/RECORD
